{"name":"Ozyegin 2019-2020 Summer","created_on":1593778127119,"courses":[{"name":"ACCT.201","title":"Finansal Muhasebe","credits":6,"class":"A","teacher":"Di̇ğdem Di̇kkaya Koloğlu","corequisite":null,"hours":[[1593506400000,1593516600000],[1593679200000,1593689400000]]},{"name":"BUS.102","title":"İşletmeye Giriş Ii (girişimcilik)","credits":4,"class":"A","teacher":"Jason Nick Shing Lau","corequisite":["BUS.102L"],"hours":[[1593506400000,1593516600000]]},{"name":"BUS.102L","title":"İşletmeye Giriş Ii (girişimcilik) - Lab.","credits":0,"class":"A","teacher":"Jason Nick Shing Lau","corequisite":["BUS.102"],"hours":[[1593517200000,1593520200000]]},{"name":"ECON.101","title":"Mikroekonomi","credits":6,"class":"A","teacher":"Gönül Şengül","corequisite":null,"hours":[[1593592800000,1593603000000],[1593679200000,1593689400000]]},{"name":"ECON.102","title":"Makroekonomi","credits":6,"class":"A","teacher":"Gönül Şengül","corequisite":null,"hours":[[1593420000000,1593430200000],[1593693600000,1593703800000]]},{"name":"FIN.202","title":"Finans","credits":6,"class":"A","teacher":"Gözde Esen","corequisite":null,"hours":[[1593510000000,1593520200000],[1593769200000,1593779400000]]},{"name":"MGMT.202","title":"Örgütler","credits":6,"class":"A","teacher":"Esra Paça","corequisite":null,"hours":[[1593420000000,1593430200000],[1593592800000,1593603000000]]},{"name":"MGMT.302","title":"Uluslararası İşletme","credits":6,"class":"A","teacher":"Ergün Önöz","corequisite":null,"hours":[[1593592800000,1593603000000],[1593682800000,1593693000000]]},{"name":"MKTG.201","title":"Pazarlama","credits":6,"class":"A","teacher":"Zeynep Mi̇na Seraj Akşi̇t","corequisite":null,"hours":[[1593528000000,1593538200000],[1593603600000,1593613800000]]},{"name":"OPER.202","title":"Operasyon Yönetimi","credits":6,"class":"A","teacher":"Nagi̇han Çömez Dolgan","corequisite":null,"hours":[[1593430800000,1593441000000],[1593607200000,1593621000000]]},{"name":"ART.301","title":"Yeni Medya Sanatına Giriş","credits":4,"class":"A","teacher":"Eda Sütunç","corequisite":null,"hours":[[1593520800000,1593531000000],[1593614400000,1593624600000]]},{"name":"HIST.103","title":"Uygarlık Tarihi I","credits":6,"class":"A","teacher":"Rami̇z Üzümçeker","corequisite":null,"hours":[[1593438000000,1593448200000],[1593614400000,1593624600000]]},{"name":"HIST.103","title":"Uygarlık Tarihi I","credits":6,"class":"B","teacher":"Rami̇z Üzümçeker","corequisite":null,"hours":[[1593520800000,1593531000000],[1593693600000,1593703800000]]},{"name":"HIST.104","title":"Uygarlık Tarihi Ii","credits":6,"class":"A","teacher":"Yener Koç","corequisite":null,"hours":[[1593445200000,1593455400000],[1593618000000,1593628200000]]},{"name":"HIST.201","title":"Atatürk İlkeleri ve İnkılap Tarihi I","credits":4,"class":"A","teacher":"Önder Uçar","corequisite":null,"hours":[[1593456000000,1593462600000],[1593628800000,1593635400000]]},{"name":"HIST.201","title":"Atatürk İlkeleri ve İnkılap Tarihi I","credits":4,"class":"B","teacher":"Önder Uçar","corequisite":null,"hours":[[1593542400000,1593549000000],[1593715200000,1593721800000]]},{"name":"HIST.202","title":"Atatürk İlkeleri ve İnkılap Tarihi Ii","credits":4,"class":"A","teacher":"Seda Özdemi̇r Şi̇mşek","corequisite":null,"hours":[[1593456000000,1593462600000],[1593628800000,1593635400000]]},{"name":"HIST.202","title":"Atatürk İlkeleri ve İnkılap Tarihi Ii","credits":4,"class":"B","teacher":"Seda Özdemi̇r Şi̇mşek","corequisite":null,"hours":[[1593542400000,1593549000000],[1593715200000,1593721800000]]},{"name":"IR.101","title":"Siyaset Bilimine Giriş","credits":6,"class":"A","teacher":"Ceren Mert Travlos","corequisite":null,"hours":[[1593592800000,1593603000000],[1593765600000,1593775800000]]},{"name":"IR.300","title":"Uluslararası İlişkiler Staj Programı","credits":4,"class":"A","teacher":"Deni̇z Sert","corequisite":null,"hours":[]},{"name":"IR.314","title":"Uluslararası Göç","credits":5,"class":"A","teacher":"Deni̇z Sert","corequisite":null,"hours":[[1593430800000,1593441000000],[1593607200000,1593617400000]]},{"name":"IR.327","title":"Kentsel Politikalar: Kentlerin Sosyolojik Olarak Okunması","credits":5,"class":"A","teacher":"Ceren Mert Travlos","corequisite":null,"hours":[[1593618000000,1593628200000],[1593787200000,1593797400000]]},{"name":"IR.390","title":"Uluslararası İlişkiler Stajı","credits":2,"class":"A","teacher":"Deni̇z Sert","corequisite":null,"hours":[]},{"name":"IR.391","title":"Uluslararası İlişkiler Stajı I","credits":1,"class":"A","teacher":"Deni̇z Sert","corequisite":null,"hours":[]},{"name":"IR.392","title":"Uluslararası İlişkiler Stajı Ii","credits":1,"class":"A","teacher":"Deni̇z Sert","corequisite":null,"hours":[]},{"name":"IR.400","title":"Uluslararası İlişkiler Araştırma Projesi","credits":4,"class":"A","teacher":"Deni̇z Sert","corequisite":null,"hours":[]},{"name":"PSY.100","title":"Genel Psikoloji","credits":6,"class":"A","teacher":"Alper Açik","corequisite":null,"hours":[[1593520800000,1593531000000],[1593693600000,1593703800000]]},{"name":"PSY.411","title":"Psikoloji Tarihi ve Felsefesi","credits":6,"class":"A","teacher":"Gökçe Tarcan Kumkale","corequisite":null,"hours":[[1593524400000,1593534600000],[1593693600000,1593703800000]]},{"name":"PSY.418","title":"Ergenlik ve Yetişkinliğe Geçiş","credits":6,"class":"A","teacher":"Ayfer Dost Gözkan","corequisite":null,"hours":[[1593513600000,1593523800000],[1593769200000,1593779400000]]},{"name":"SOC.201","title":"Sosyal Bilimlere Giriş","credits":6,"class":"A","teacher":"Alpkan Bi̇relma","corequisite":null,"hours":[[1593592800000,1593603000000],[1593679200000,1593689400000]]},{"name":"SOC.201","title":"Sosyal Bilimlere Giriş","credits":6,"class":"B","teacher":"Susan Beth Rottmann","corequisite":null,"hours":[[1593592800000,1593603000000],[1593679200000,1593689400000]]},{"name":"TLL.101","title":"Türk Dili ve Edebiyatı I","credits":4,"class":"A","teacher":"Ezgi̇ Hamzaçebi̇","corequisite":null,"hours":[[1593787200000,1593801000000]]},{"name":"TLL.101","title":"Türk Dili ve Edebiyatı I","credits":4,"class":"B","teacher":"Ezgi̇ Hamzaçebi̇","corequisite":null,"hours":[[1593690000000,1593703800000]]},{"name":"TLL.102","title":"Türk Dili ve Edebiyatı Ii","credits":4,"class":"A","teacher":"İbrahi̇m Öztürk","corequisite":null,"hours":[[1593787200000,1593801000000]]},{"name":"TLL.102","title":"Türk Dili ve Edebiyatı Ii","credits":4,"class":"B","teacher":"İbrahi̇m Öztürk","corequisite":null,"hours":[[1593765600000,1593779400000]]},{"name":"AVM.303","title":"Hava Trafik ve Meteoroloji","credits":4,"class":"A","teacher":"Mehmet Ertürk","corequisite":null,"hours":[[1593610800000,1593621000000],[1593682800000,1593693000000]]},{"name":"AVM.405","title":"Emniyet Yönetimi Sistemi","credits":6,"class":"A","teacher":"Hüseyi̇n Önder Aldemi̇r","corequisite":null,"hours":[[1593438000000,1593448200000],[1593596400000,1593606600000]]},{"name":"AVM.408","title":"Havacılık Yönetiminde Öngörü ve Optimizasyon","credits":6,"class":"A","teacher":"Cem Ersöz","corequisite":null,"hours":[[1593520800000,1593531000000],[1593693600000,1593703800000]]},{"name":"PLT.208","title":"Gece Uçuş Uygulaması","credits":4,"class":"A","teacher":"Mehmet Bülent Aksum","corequisite":null,"hours":[]},{"name":"PLT.210","title":"Pic Uçuş Uygulaması I","credits":2,"class":"A","teacher":"Mehmet Bülent Aksum","corequisite":null,"hours":[]},{"name":"PLT.221","title":"Emniyet Yönetim Sistemi","credits":6,"class":"A","teacher":"Hüseyi̇n Önder Aldemi̇r","corequisite":null,"hours":[[1593438000000,1593448200000],[1593596400000,1593606600000]]},{"name":"PLT.311","title":"Meteoroloji (atpl)","credits":6,"class":"A","teacher":"Bahadir Tanyolaç","corequisite":null,"hours":[[1593420000000,1593430200000],[1593434400000,1593444600000],[1593506400000,1593516600000],[1593520800000,1593531000000]]},{"name":"PLT.313","title":"Havacılık İngilizcesi","credits":6,"class":"A","teacher":"Petek Şi̇ri̇n","corequisite":null,"hours":[[1593592800000,1593603000000],[1593679200000,1593689400000]]},{"name":"PLT.318","title":"Pic Uçuş Uygulaması Ii","credits":2,"class":"A","teacher":"Mehmet Bülent Aksum","corequisite":null,"hours":[]},{"name":"CE.203","title":"Mukavemet","credits":6,"class":"A","teacher":"Ahmet Yi̇ği̇t Özçeli̇k","corequisite":null,"hours":[[1593434400000,1593448200000],[1593506400000,1593520200000]]},{"name":"CS.401","title":"Bilgisayar Mühendisliği Bitirme Projesi I","credits":4,"class":"A","teacher":"Mustafa Furkan Kiraç","corequisite":null,"hours":[]},{"name":"CS.402","title":"Bilgisayar Mühendisliği Bitirme Projesi Ii","credits":4,"class":"A","teacher":"Mustafa Furkan Kiraç","corequisite":null,"hours":[]},{"name":"EE.401","title":"Elektrik-elektronik Mühendisliği Bitirme Projesi I","credits":4,"class":"A","teacher":"Kadi̇r Durak","corequisite":null,"hours":[[1593697200000,1593700200000]]},{"name":"EE.402","title":"Elektrik-elektronik Mühendisliği Bitirme Projesi Ii","credits":4,"class":"A","teacher":"Kadi̇r Durak","corequisite":null,"hours":[[1593697200000,1593700200000]]},{"name":"IE.201","title":"Yöneylem Araştırması I","credits":6,"class":"A","teacher":"Mehmet Önal","corequisite":["IE.201R"],"hours":[[1593445200000,1593455400000],[1593528000000,1593538200000]]},{"name":"IE.201R","title":"Yöneylem Araştırması I - Rec.","credits":0,"class":"A","teacher":"Mehmet Önal","corequisite":["IE.201"],"hours":[[1593769200000,1593779400000]]},{"name":"IE.246","title":"Yöneylem Araştırması için Programlama","credits":6,"class":"A","teacher":"Umut Beşi̇kci̇","corequisite":["IE.246R"],"hours":[[1593434400000,1593444600000],[1593517200000,1593527400000]]},{"name":"IE.246R","title":"Yöneylem Araştırması için Programlama - Uygulama","credits":0,"class":"A","teacher":"Umut Beşi̇kci̇","corequisite":["IE.246"],"hours":[[1593592800000,1593603000000]]},{"name":"IE.301","title":"Yöneylem Araştırması Ii","credits":6,"class":"A","teacher":"Ümmühan Akbay","corequisite":["IE.301R"],"hours":[[1593506400000,1593516600000],[1593592800000,1593603000000]]},{"name":"IE.301R","title":"Yöneylem Araştırması 2 - Uygulama","credits":0,"class":"A","teacher":"Ümmühan Akbay","corequisite":["IE.301"],"hours":[[1593607200000,1593617400000]]},{"name":"IE.302","title":"Üretim Sistemleri Analizi","credits":6,"class":"A","teacher":"Ertan Yakici","corequisite":["IE.302R"],"hours":[[1593528000000,1593538200000],[1593618000000,1593628200000]]},{"name":"IE.302R","title":"Üretim Sistemleri Analizi - Uygulama ","credits":0,"class":"A","teacher":"Ertan Yakici","corequisite":["IE.302"],"hours":[[1593769200000,1593779400000]]},{"name":"IE.325","title":"Benzetişim Modellemesi ve Analizi","credits":6,"class":"A","teacher":"İsmai̇l Başoğlu","corequisite":["IE.325R"],"hours":[[1593592800000,1593603000000],[1593679200000,1593689400000]]},{"name":"IE.325R","title":"Benzetişim Modellemesi ve Analizi - Uygulama","credits":0,"class":"A","teacher":"İsmai̇l Başoğlu","corequisite":["IE.325"],"hours":[[1593603600000,1593613800000]]},{"name":"IE.342","title":"Matematiksel Modelleme ve Kesin Metodlar","credits":6,"class":"A","teacher":"Gökalp Erbeyoğlu","corequisite":["IE.342R"],"hours":[[1593690000000,1593700200000],[1593704400000,1593714600000]]},{"name":"IE.342R","title":"Matematiksel Modelleme ve Kesin Metodlar Uygulama","credits":0,"class":"A","teacher":"Gökalp Erbeyoğlu","corequisite":["IE.342"],"hours":[[1593787200000,1593797400000]]},{"name":"IE.362","title":"Risk Yönetimi","credits":6,"class":"A","teacher":"Bora Tokgöz","corequisite":null,"hours":[[1593434400000,1593455400000]]},{"name":"MATH.101","title":"Sosyal Bilimler için Matematik I","credits":6,"class":"A","teacher":"Berkay Anahtarci","corequisite":null,"hours":[[1593423600000,1593433800000],[1593510000000,1593520200000]]},{"name":"MATH.102","title":"Sosyal Bilimler için Matematik Ii","credits":6,"class":"A","teacher":"Uğur Doğan","corequisite":null,"hours":[[1593445200000,1593455400000],[1593603600000,1593613800000]]},{"name":"MATH.104","title":"Mühendislik için Yüksek Matematik Ii","credits":8,"class":"A","teacher":"Uğur Doğan","corequisite":["MATH.104R"],"hours":[[1593520800000,1593531000000],[1593708000000,1593718200000]]},{"name":"MATH.104R","title":"Mühendislik için Yüksek Matematik Ii - Rec.","credits":0,"class":"A","teacher":"Uğur Doğan","corequisite":["MATH.104"],"hours":[[1593787200000,1593801000000]]},{"name":"MATH.112","title":"Ayrık Matematik","credits":6,"class":"A","teacher":"Mehmet Öz","corequisite":null,"hours":[[1593438000000,1593448200000],[1593769200000,1593779400000]]},{"name":"MATH.201","title":"Sosyal Bilimler için Olasılık","credits":6,"class":"A","teacher":"Biliana Stefanova Gyuner","corequisite":null,"hours":[[1593517200000,1593527400000],[1593690000000,1593700200000],[1593772800000,1593775800000]]},{"name":"MATH.202","title":"Sosyal Bilimler için İstatistik","credits":6,"class":"A","teacher":"Biliana Stefanova Gyuner","corequisite":null,"hours":[[1593528000000,1593538200000],[1593700800000,1593711000000],[1593787200000,1593790200000]]},{"name":"MATH.211","title":"Doğrusal Cebir","credits":6,"class":"A","teacher":"Çağatay Edemen","corequisite":null,"hours":[[1593420000000,1593433800000],[1593592800000,1593606600000]]},{"name":"MATH.212","title":"Diferansiyel Denklemler","credits":6,"class":"A","teacher":"Berkay Anahtarci","corequisite":null,"hours":[[1593614400000,1593628200000],[1593679200000,1593693000000]]},{"name":"MATH.215","title":"Olasılık ve Rassal Değişkenler","credits":6,"class":"A","teacher":"İsmai̇l Başoğlu","corequisite":["MATH.215R"],"hours":[[1593618000000,1593628200000],[1593690000000,1593700200000]]},{"name":"MATH.215R","title":"Olasılık ve Rassal Değişkenler - Rec.","credits":0,"class":"A","teacher":"İsmai̇l Başoğlu","corequisite":["MATH.215"],"hours":[[1593704400000,1593714600000]]},{"name":"MATH.216","title":"Uygulamalı İstatistik","credits":6,"class":"A","teacher":"Mehmet Güray Güler","corequisite":["MATH216R"],"hours":[[1593506400000,1593516600000],[1593603600000,1593613800000]]},{"name":"MATH.216R","title":"Uygulamalı istatistik - Uygulama ","credits":0,"class":"A","teacher":"Mehmet Güray Güler","corequisite":["MATH.216"],"hours":[[1593700800000,1593711000000]]},{"name":"MATH.217","title":"Olasılık ve İstatistik","credits":6,"class":"A","teacher":"Çağatay Edemen","corequisite":null,"hours":[[1593506400000,1593520200000],[1593765600000,1593779400000]]},{"name":"PHYS.101","title":"Fizik I","credits":8,"class":"A","teacher":"Alper Hayreter","corequisite":["PHYS.101L"],"hours":[[1593607200000,1593621000000],[1593690000000,1593703800000]]},{"name":"PHYS.101L","title":"Fizik I - Lab.","credits":0,"class":"A","teacher":"Alper Hayreter","corequisite":["PHYS.101"],"hours":[]},{"name":"PHYS.102","title":"Fizik Ii","credits":8,"class":"A","teacher":"Bora Işildak","corequisite":["PHYS.102L"],"hours":[[1593506400000,1593520200000],[1593693600000,1593707400000]]},{"name":"PHYS.102L","title":"Fizik Ii - Lab.","credits":0,"class":"A","teacher":"Bora Işildak","corequisite":["PHYS.102"],"hours":[]},{"name":"PHYS.104","title":"Havacılık için Fizik Ii","credits":6,"class":"A","teacher":"Mehmet Burçi̇n Ünlü","corequisite":["PHYS.104L","PHYS.104R"],"hours":[[1593506400000,1593520200000]]},{"name":"PHYS.104L","title":"Havacılık için Fizik Ii - Lab.","credits":0,"class":"A","teacher":"Mehmet Burçi̇n Ünlü","corequisite":["PHYS.104","PHYS.104R"],"hours":[]},{"name":"PHYS.104R","title":"Havacılık için Fizik Ii - Rec.","credits":0,"class":"A","teacher":"Mehmet Burçi̇n Ünlü","corequisite":["PHYS.104","PHYS.104L"],"hours":[[1593679200000,1593693000000]]},{"name":"ARB.201","title":"Arapça Iii","credits":5,"class":"A","teacher":"Salma Jehad Awad Alamassi","corequisite":null,"hours":[[1593438000000,1593448200000],[1593614400000,1593624600000],[1593700800000,1593707400000]]},{"name":"CHN.201","title":"Çince Iii","credits":5,"class":"A","teacher":"Lale Güner","corequisite":null,"hours":[[1593438000000,1593448200000],[1593614400000,1593624600000],[1593700800000,1593707400000]]},{"name":"ENG.101","title":"İngilizce I","credits":4,"class":"A","teacher":"Mehmet Demi̇r","corequisite":null,"hours":[[1593434400000,1593444600000],[1593520800000,1593531000000],[1593704400000,1593711000000]]},{"name":"ENG.101","title":"İngilizce I","credits":4,"class":"B","teacher":"Bedra Betül Şenol","corequisite":null,"hours":[[1593531600000,1593541800000],[1593603600000,1593613800000],[1593686400000,1593693000000]]},{"name":"ENG.101","title":"İngilizce I","credits":4,"class":"C","teacher":"Selen Yildiz","corequisite":null,"hours":[[1593423600000,1593433800000],[1593596400000,1593606600000],[1593682800000,1593689400000]]},{"name":"ENG.101","title":"İngilizce I","credits":4,"class":"D","teacher":"Ayla Yalçin Duman","corequisite":null,"hours":[[1593520800000,1593531000000],[1593596400000,1593606600000],[1593772800000,1593779400000]]},{"name":"ENG.102","title":"İngilizce Ii","credits":3,"class":"A","teacher":"Zeynep Şebnem Bayraktar","corequisite":null,"hours":[[1593434400000,1593444600000],[1593524400000,1593534600000],[1593704400000,1593711000000]]},{"name":"ENG.102","title":"İngilizce Ii","credits":3,"class":"B","teacher":"Ayşe Nesli̇han Sabuncu","corequisite":null,"hours":[[1593420000000,1593430200000],[1593531600000,1593541800000],[1593704400000,1593711000000]]},{"name":"ENG.102","title":"İngilizce Ii","credits":3,"class":"C","teacher":"Burak Şenel","corequisite":null,"hours":[[1593423600000,1593433800000],[1593596400000,1593606600000],[1593682800000,1593689400000]]},{"name":"ENG.102","title":"İngilizce Ii","credits":3,"class":"D","teacher":"İlkay Tuzcu Tiğli","corequisite":null,"hours":[[1593513600000,1593523800000],[1593610800000,1593621000000],[1593772800000,1593779400000]]},{"name":"ENG.103","title":"İngilizce I (türkçe Programlar)","credits":4,"class":"A","teacher":"Azra Ni̇hal Yilmaz","corequisite":null,"hours":[[1593513600000,1593523800000],[1593610800000,1593621000000]]},{"name":"ENG.104","title":"İngilizce Ii (türkçe Programlar)","credits":3,"class":"A","teacher":"Ayfer Karaca","corequisite":null,"hours":[[1593531600000,1593541800000],[1593618000000,1593628200000]]},{"name":"ENG.105","title":"İngilizce Konuşma Becerileri I","credits":4,"class":"A","teacher":"Marija Vella","corequisite":null,"hours":[[1593686400000,1593696600000],[1593769200000,1593779400000]]},{"name":"ENG.106","title":"İngilizce Konuşma Becerileri Ii","credits":3,"class":"A","teacher":"Saadet Tikaç","corequisite":null,"hours":[[1593610800000,1593621000000],[1593693600000,1593703800000]]},{"name":"ENG.303","title":"Teknik İletişim","credits":2,"class":"A","teacher":"Ali Nezami","corequisite":null,"hours":[[1593423600000,1593433800000],[1593679200000,1593689400000]]},{"name":"FRE.202","title":"Fransızca Iv","credits":5,"class":"A","teacher":"Eugene Giovanelli","corequisite":null,"hours":[[1593510000000,1593520200000],[1593607200000,1593617400000],[1593772800000,1593779400000]]},{"name":"GER.102","title":"Almanca Ii","credits":5,"class":"A","teacher":"Ti̇jen Bayar Kuli̇ğ","corequisite":null,"hours":[[1593427200000,1593437400000],[1593517200000,1593527400000],[1593603600000,1593610200000]]},{"name":"GER.201","title":"Almanca Iii","credits":5,"class":"A","teacher":"Nuran Uysal Duman","corequisite":null,"hours":[[1593438000000,1593448200000],[1593614400000,1593624600000],[1593700800000,1593707400000]]},{"name":"GER.202","title":"Almanca Iv","credits":5,"class":"A","teacher":"Handa Yildiz","corequisite":null,"hours":[[1593430800000,1593441000000],[1593610800000,1593621000000],[1593693600000,1593700200000]]},{"name":"ITA.202","title":"İtalyanca Iv","credits":5,"class":"A","teacher":"Arco Jannuzzi̇","corequisite":null,"hours":[[1593438000000,1593448200000],[1593524400000,1593534600000],[1593700800000,1593707400000]]},{"name":"RUS.202","title":"Rusça Iv","credits":5,"class":"A","teacher":"Olga Mi̇reli̇","corequisite":null,"hours":[[1593524400000,1593534600000],[1593700800000,1593711000000],[1593787200000,1593793800000]]},{"name":"SPA.102","title":"İspanyolca Ii","credits":5,"class":"A","teacher":"Jose Ramon Cruz Escudero","corequisite":null,"hours":[[1593441600000,1593451800000],[1593596400000,1593606600000],[1593790800000,1593797400000]]},{"name":"SPA.201","title":"İspanyolca Iii","credits":5,"class":"A","teacher":"Ervin Daleth Ostos Santos","corequisite":null,"hours":[[1593438000000,1593448200000],[1593614400000,1593624600000],[1593700800000,1593707400000]]},{"name":"SPA.202","title":"İspanyolca Iv","credits":5,"class":"A","teacher":"Meltem Michele Martinez Velasco","corequisite":null,"hours":[[1593531600000,1593541800000],[1593700800000,1593711000000],[1593794400000,1593801000000]]},{"name":"TURK.102","title":"Yabancılar için Türkçe Ii","credits":4,"class":"A","teacher":"Asli Bektaş","corequisite":null,"hours":[[1593542400000,1593549000000],[1593715200000,1593721800000],[1593787200000,1593793800000]]},{"name":"ARCH.102","title":"Mimari Tasarım Stüdyosu  I","credits":10,"class":"A","teacher":"Gülden Canol","corequisite":null,"hours":[[1593420000000,1593455400000],[1593679200000,1593714600000]]},{"name":"ARCH.200","title":"Araştırma Stajı","credits":2,"class":"A","teacher":"Orhan Hacihasanoğlu","corequisite":null,"hours":[]},{"name":"ARCH.201","title":"Mimari Tasarım Stüdyosu Ii","credits":10,"class":"A","teacher":"Gülnar Ocakdan Karaytuğ","corequisite":null,"hours":[[1593420000000,1593455400000],[1593679200000,1593714600000]]},{"name":"ARCH.202","title":"Mimari Tasarım Stüdyosu Iii","credits":10,"class":"A","teacher":"Si̇nan Özgen","corequisite":null,"hours":[[1593420000000,1593455400000],[1593679200000,1593714600000]]},{"name":"ARCH.300","title":"Yaz Stajı Ii (büro Stajı)","credits":2,"class":"A","teacher":"Orhan Hacihasanoğlu","corequisite":null,"hours":[]},{"name":"ARCH.301","title":"Mimari Tasarım Stüdyosu  Iv","credits":10,"class":"A","teacher":"Berke Hati̇poğlu","corequisite":null,"hours":[[1593420000000,1593455400000],[1593679200000,1593714600000]]},{"name":"ARCH.302","title":"Mimari Tasarım Stüdyosu  V","credits":10,"class":"A","teacher":"Hakan Dölgen","corequisite":null,"hours":[[1593420000000,1593455400000],[1593679200000,1593714600000]]},{"name":"ARCH.400","title":"Yaz Stajı Iii (şantiye)","credits":4,"class":"A","teacher":"Orhan Hacihasanoğlu","corequisite":null,"hours":[]},{"name":"ARCH.401","title":"Mimari Tasarım Stüdyosu Vi","credits":12,"class":"A","teacher":"Ni̇hat Gündüz","corequisite":null,"hours":[[1593420000000,1593455400000],[1593679200000,1593714600000]]},{"name":"ARCH.445","title":"İslam Mimarisi","credits":3,"class":"A","teacher":"Meli̇s Taner","corequisite":null,"hours":[[1593524400000,1593538200000]]},{"name":"ARCH.460","title":"Mimarlık ve Tasarımda Küresel Çalışmalar ","credits":3,"class":"A","teacher":"Alessandro Camiz","corequisite":null,"hours":[[1593765600000,1593779400000]]},{"name":"ARCH.460","title":"Mimarlık ve Tasarımda Küresel Çalışmalar ","credits":3,"class":"B","teacher":"Alessandro Camiz","corequisite":null,"hours":[[1593787200000,1593801000000]]},{"name":"COD.200","title":"Yaz Stajı I","credits":2,"class":"A","teacher":"Orhan Hacihasanoğlu","corequisite":null,"hours":[]},{"name":"COD.300","title":"Yaz Stajı Ii","credits":2,"class":"A","teacher":"Orhan Hacihasanoğlu","corequisite":null,"hours":[]},{"name":"COD.400","title":"Yaz Stajı Iii","credits":2,"class":"A","teacher":"Orhan Hacihasanoğlu","corequisite":null,"hours":[]},{"name":"IDE.100","title":"Yaz Stajı I","credits":2,"class":"A","teacher":"Orhan Hacihasanoğlu","corequisite":null,"hours":[]},{"name":"IDE.200","title":"Yaz Stajı Ii (ofis)","credits":2,"class":"A","teacher":"Orhan Hacihasanoğlu","corequisite":null,"hours":[]},{"name":"IDE.201","title":"Tasarım Stüdyosu I","credits":10,"class":"A","teacher":"Can Arbak","corequisite":null,"hours":[[1593420000000,1593455400000],[1593679200000,1593714600000]]},{"name":"IDE.202","title":"Tasarım Stüdyosu 2","credits":10,"class":"A","teacher":"Can Arbak","corequisite":null,"hours":[[1593420000000,1593455400000],[1593679200000,1593714600000]]},{"name":"IDE.300","title":"Yaz Stajı Iii (fabrika)","credits":4,"class":"A","teacher":"Orhan Hacihasanoğlu","corequisite":null,"hours":[]},{"name":"IDE.301","title":"Tasarım Stüdyosu 3","credits":10,"class":"A","teacher":"Can Arbak","corequisite":null,"hours":[[1593420000000,1593455400000],[1593679200000,1593714600000]]},{"name":"IDE.302","title":"Tasarım Stüdyosu 4","credits":10,"class":"A","teacher":"Can Arbak","corequisite":null,"hours":[[1593420000000,1593455400000],[1593679200000,1593714600000]]},{"name":"INAR.200","title":"Yaz Stajı I (araştırma Stajı)","credits":2,"class":"A","teacher":"Orhan Hacihasanoğlu","corequisite":null,"hours":[]},{"name":"INAR.201","title":"İç Mimarlık Tasarım Stüdyosu I","credits":10,"class":"A","teacher":"Pinar Artikoğlu","corequisite":null,"hours":[[1593420000000,1593455400000],[1593679200000,1593714600000]]},{"name":"INAR.202","title":"İç Mimarlık Tasarım Stüdyosu Ii","credits":10,"class":"A","teacher":"Pinar Artikoğlu","corequisite":null,"hours":[[1593420000000,1593455400000],[1593679200000,1593714600000]]},{"name":"INAR.300","title":"Yaz Stajı Ii (büro Stajı)","credits":2,"class":"A","teacher":"Orhan Hacihasanoğlu","corequisite":null,"hours":[]},{"name":"INAR.301","title":"İç Mimarlık Tasarım Stüdyosu Iii","credits":10,"class":"A","teacher":"Mi̇ne Arbay","corequisite":null,"hours":[[1593420000000,1593455400000],[1593679200000,1593714600000]]},{"name":"INAR.302","title":"İç Mimarlık Tasarım Stüdyosu Iv","credits":10,"class":"A","teacher":"Mi̇ne Arbay","corequisite":null,"hours":[[1593420000000,1593455400000],[1593679200000,1593714600000]]},{"name":"INAR.400","title":"Yaz Stajı Iii (şantiye Stajı)","credits":4,"class":"A","teacher":"Orhan Hacihasanoğlu","corequisite":null,"hours":[]},{"name":"MİM.102","title":"Mimari Tasarım Stüdyosu I","credits":10,"class":"A","teacher":"Gülden Canol","corequisite":null,"hours":[[1593420000000,1593455400000],[1593679200000,1593714600000]]},{"name":"MİM.200","title":"Yaz Stajı I (araştırma)","credits":2,"class":"A","teacher":"Orhan Hacihasanoğlu","corequisite":null,"hours":[]},{"name":"MİM.201","title":"Mimari Tasarım Stüdyosu Ii","credits":10,"class":"A","teacher":"Gülnar Ocakdan Karaytuğ","corequisite":null,"hours":[[1593420000000,1593455400000],[1593679200000,1593714600000]]},{"name":"MİM.202","title":"Mimari Tasarım Stüdyosu Iii","credits":10,"class":"A","teacher":"Si̇nan Özgen","corequisite":null,"hours":[[1593420000000,1593455400000],[1593679200000,1593714600000]]},{"name":"MİM.300","title":"Yaz Stajı Ii (büro)","credits":2,"class":"A","teacher":"Orhan Hacihasanoğlu","corequisite":null,"hours":[]},{"name":"MİM.301","title":"Mimari Tasarım Stüdyosu Iv","credits":10,"class":"A","teacher":"Berke Hati̇poğlu","corequisite":null,"hours":[[1593420000000,1593455400000],[1593679200000,1593714600000]]},{"name":"MİM.302","title":"Mimari Tasarım Stüdyosu V","credits":10,"class":"A","teacher":"Hakan Dölgen","corequisite":null,"hours":[[1593420000000,1593455400000],[1593679200000,1593714600000]]},{"name":"MİM.400","title":"Yaz Stajı Iii (şantiye Stajı)","credits":4,"class":"A","teacher":"Orhan Hacihasanoğlu","corequisite":null,"hours":[]},{"name":"MİM.401","title":"Mimari Tasarım Stüdyosu Vi","credits":12,"class":"A","teacher":"Ni̇hat Gündüz","corequisite":null,"hours":[[1593420000000,1593455400000],[1593679200000,1593714600000]]},{"name":"HUK.102","title":"Roma Hukuku Özel Hükümler","credits":2,"class":"A","teacher":"Zeli̇ha Bengi̇ Berk Eri̇şi̇r","corequisite":null,"hours":[[1593592800000,1593603000000],[1593697200000,1593707400000]]},{"name":"HUK.105","title":"Anayasa Hukuku I","credits":4,"class":"A","teacher":"Murat Tumay","corequisite":null,"hours":[[1593528000000,1593541800000],[1593700800000,1593714600000]]},{"name":"HUK.106","title":"Anayasa Hukuku Ii","credits":4,"class":"A","teacher":"Murat Tumay","corequisite":null,"hours":[[1593506400000,1593520200000],[1593679200000,1593693000000]]},{"name":"HUK.107","title":"Medeni Hukuk I: Giriş, Temel Kavramlar,  Kişiler Hukuku","credits":4,"class":"A","teacher":"Tuğçe Tuzcuoğlu","corequisite":null,"hours":[[1593596400000,1593610200000],[1593765600000,1593779400000]]},{"name":"HUK.108","title":"Medeni Hukuk Ii: Aile Hukuku","credits":4,"class":"A","teacher":"Hande Deni̇z","corequisite":null,"hours":[[1593420000000,1593430200000],[1593765600000,1593775800000]]},{"name":"HUK.109","title":"Hukuka Giriş","credits":2,"class":"A","teacher":"Özge Di̇dem Boulanger","corequisite":null,"hours":[[1593434400000,1593448200000]]},{"name":"HUK.110","title":"Hukukçular için İktisat","credits":2,"class":"A","teacher":"Hani̇fe Ni̇lüfer Uğur Dalay","corequisite":null,"hours":[[1593438000000,1593451800000]]},{"name":"HUK.201","title":"Ceza Hukuku Genel Hükümler I","credits":6,"class":"A","teacher":"Zafer İçer","corequisite":null,"hours":[[1593610800000,1593624600000],[1593679200000,1593693000000]]},{"name":"HUK.202","title":"Ceza Hukuku Genel Hükümler Ii","credits":6,"class":"A","teacher":"Zafer İçer","corequisite":null,"hours":[[1593592800000,1593606600000],[1593700800000,1593714600000]]},{"name":"HUK.203","title":"İdare Hukuku I","credits":4,"class":"A","teacher":"Hasan Dursun","corequisite":null,"hours":[[1593420000000,1593433800000],[1593506400000,1593520200000]]},{"name":"HUK.204","title":"İdare Hukuku Ii","credits":4,"class":"A","teacher":"Hayri̇ye Bi̇ge Açimuz","corequisite":null,"hours":[[1593510000000,1593523800000],[1593682800000,1593696600000]]},{"name":"HUK.205","title":"Borçlar Hukuku Genel Hükümler I","credits":6,"class":"A","teacher":"Tülay Aydin Ünver","corequisite":null,"hours":[[1593697200000,1593711000000],[1593787200000,1593801000000]]},{"name":"HUK.206","title":"Borçlar Hukuku Genel Hükümler Ii","credits":6,"class":"A","teacher":"Tuğçe Tuzcuoğlu","corequisite":null,"hours":[[1593614400000,1593628200000],[1593787200000,1593801000000]]},{"name":"HUK.207","title":"Devletler Genel Hukuku I","credits":4,"class":"A","teacher":"Tülay Yildirim Mat","corequisite":null,"hours":[[1593524400000,1593538200000]]},{"name":"HUK.213","title":"Hukuk Felsefesi ve Sosyolojisi I","credits":2,"class":"A","teacher":"Mehmet Altan Heper","corequisite":null,"hours":[[1593765600000,1593779400000]]},{"name":"HUK.214","title":"Hukuk Felsefesi ve Sosyolojisi Ii","credits":2,"class":"A","teacher":"Mehmet Altan Heper","corequisite":null,"hours":[[1593441600000,1593455400000]]},{"name":"HUK.221","title":"Kriminoloji","credits":2,"class":"A","teacher":"Hasan Dursun","corequisite":null,"hours":[[1593765600000,1593779400000]]},{"name":"HUK.239","title":"Basın Hukuku","credits":2,"class":"A","teacher":"Ramazan Bariş Atladi","corequisite":null,"hours":[[1593456000000,1593469800000]]},{"name":"HUK.301","title":"Ceza Hukuku Özel Hükümler I","credits":3,"class":"A","teacher":"Ramazan Bariş Atladi","corequisite":null,"hours":[[1593441600000,1593455400000]]},{"name":"HUK.302","title":"Ceza Hukuku Özel Hükümler Ii","credits":3,"class":"A","teacher":"Ramazan Bariş Atladi","corequisite":null,"hours":[[1593765600000,1593779400000]]},{"name":"HUK.305","title":"Ticaret Hukuku I: Genel Hükümler, Ticari İşletme, Kıymetli Evrak","credits":5,"class":"A","teacher":"Sami̇ Kocabiyik","corequisite":null,"hours":[[1593524400000,1593538200000],[1593787200000,1593801000000]]},{"name":"HUK.306","title":"Ticaret Hukuku Ii: Ortaklıklar Hukuku","credits":4,"class":"A","teacher":"Işik Özer","corequisite":null,"hours":[[1593506400000,1593520200000],[1593787200000,1593801000000]]},{"name":"HUK.307","title":"Eşya Hukuku I","credits":5,"class":"A","teacher":"Melek Yüce","corequisite":null,"hours":[[1593596400000,1593606600000],[1593693600000,1593703800000]]},{"name":"HUK.308","title":"Eşya Hukuku Ii","credits":4,"class":"A","teacher":"Melek Yüce","corequisite":null,"hours":[[1593618000000,1593628200000],[1593704400000,1593714600000]]},{"name":"HUK.309","title":"Genel Kamu Hukuku","credits":2,"class":"A","teacher":"Özge Yücel Deri̇ci̇ler","corequisite":null,"hours":[[1593438000000,1593451800000]]},{"name":"HUK.310","title":"İnsan Hakları Hukuku","credits":2,"class":"A","teacher":"Özge Yücel Deri̇ci̇ler","corequisite":null,"hours":[[1593423600000,1593437400000]]},{"name":"HUK.314","title":"Şirket Kurma","credits":2,"class":"A","teacher":"Sami̇ Kocabiyik","corequisite":["HUK.306"],"hours":[[1593427200000,1593441000000]]},{"name":"HUK.314","title":"Şirket Kurma","credits":2,"class":"B","teacher":"Sami̇ Kocabiyik","corequisite":["HUK.306"],"hours":[[1593801600000,1593815400000]]},{"name":"HUK.315","title":"İdari Yargılama Hukuku","credits":2,"class":"A","teacher":"Hasan Dursun","corequisite":null,"hours":[[1593528000000,1593541800000]]},{"name":"HUK.317","title":"Avrupa Birliği Teşkilatı ve Hukuku","credits":2,"class":"A","teacher":"Özlem Armağan","corequisite":null,"hours":[[1593765600000,1593779400000]]},{"name":"HUK.319","title":"Kamu Maliyesi ve Vergi Hukuku I","credits":3,"class":"A","teacher":"Hamdi̇ Deni̇z Ege Göktuna","corequisite":null,"hours":[[1593456000000,1593466200000],[1593542400000,1593552600000]]},{"name":"HUK.320","title":"Kamu Maliyesi ve Vergi Hukuku Ii","credits":2,"class":"A","teacher":"Hamdi̇ Deni̇z Ege Göktuna","corequisite":null,"hours":[[1593679200000,1593693000000]]},{"name":"HUK.322","title":"Rekabet Hukuku","credits":2,"class":"A","teacher":"Sami̇ Kocabiyik","corequisite":null,"hours":[[1593542400000,1593556200000]]},{"name":"HUK.327","title":"Spor Hukuku","credits":2,"class":"A","teacher":"Gürkan Özocak","corequisite":null,"hours":[[1593607200000,1593621000000]]},{"name":"HUK.328","title":"Uluslararası Taşıma Hukuku","credits":2,"class":"A","teacher":"Ayça Uçar","corequisite":null,"hours":[[1593596400000,1593610200000]]},{"name":"HUK.401","title":"Ceza Muhakemesi Hukuku I","credits":5,"class":"A","teacher":"Vesi̇le Sonay Evi̇k","corequisite":null,"hours":[[1593420000000,1593433800000],[1593520800000,1593534600000]]},{"name":"HUK.402","title":"Ceza Muhakemesi Hukuku Ii","credits":6,"class":"A","teacher":"Vesi̇le Sonay Evi̇k","corequisite":null,"hours":[[1593434400000,1593448200000],[1593506400000,1593520200000]]},{"name":"HUK.403","title":"Miras Hukuku","credits":4,"class":"A","teacher":"Tülay Aydin Ünver","corequisite":null,"hours":[[1593441600000,1593451800000],[1593506400000,1593516600000]]},{"name":"HUK.404","title":"Deniz Ticaret Hukuku","credits":4,"class":"A","teacher":"Gülfer Meri̇ç","corequisite":null,"hours":[[1593420000000,1593430200000],[1593686400000,1593696600000]]},{"name":"HUK.405","title":"Devletler Özel Hukuku I","credits":4,"class":"A","teacher":"Nuray Ekşi̇","corequisite":null,"hours":[[1593592800000,1593606600000],[1593697200000,1593711000000]]},{"name":"HUK.406","title":"Devletler Özel Hukuku Ii","credits":4,"class":"A","teacher":"Jocelyne Alayan","corequisite":null,"hours":[[1593520800000,1593534600000],[1593787200000,1593801000000]]},{"name":"HUK.410","title":"İş ve Sosyal Güvenlik Hukuku Ii","credits":4,"class":"A","teacher":"Akin Kivrakdal","corequisite":null,"hours":[[1593610800000,1593624600000],[1593697200000,1593711000000]]},{"name":"HUK.413","title":"Sigorta Hukuku","credits":4,"class":"A","teacher":"Gülfer Meri̇ç","corequisite":null,"hours":[[1593787200000,1593801000000]]},{"name":"HUK.415","title":"Fikri ve Sinai Mülkiyet Hukuku","credits":2,"class":"A","teacher":"Işik Özer","corequisite":null,"hours":[[1593765600000,1593779400000]]},{"name":"HUK.424","title":"Ceza İnfaz Hukuku","credits":2,"class":"A","teacher":"Ramazan Bariş Atladi","corequisite":null,"hours":[[1593801600000,1593815400000]]},{"name":"HUK.444","title":"Patent Hukuku","credits":2,"class":"A","teacher":"Sami̇ Kocabiyik","corequisite":null,"hours":[[1593715200000,1593729000000]]},{"name":"HUK.492","title":"İş Hukukunda Güncel Sorunlar","credits":2,"class":"A","teacher":"Akin Kivrakdal","corequisite":null,"hours":[[1593628800000,1593642600000]]},{"name":"HUK.493","title":"Çocuk Hakları Perspektifinden Özel Hukuk","credits":2,"class":"A","teacher":"Sevgi̇ Usta","corequisite":null,"hours":[[1593801600000,1593815400000]]},{"name":"LAW.241","title":"İslam Hukuku ve Modern Dünya","credits":4,"class":"A","teacher":"Jocelyne Alayan","corequisite":null,"hours":[[1593452400000,1593466200000]]},{"name":"LAW.447","title":"Uluslararası Ticaret","credits":4,"class":"A","teacher":"Ayça Uçar","corequisite":null,"hours":[[1593679200000,1593693000000]]}]}